instaspy/__init__.py
instaspy/config.py
instaspy/exceptions.py
instaspy-1.0.3.dist-info/METADATA
instaspy-1.0.3.dist-info/WHEEL
instaspy-1.0.3.dist-info/top_level.txt
instaspy-1.0.3.dist-info/RECORD
