Metadata-Version: 2.4
Name: InstaSpy
Version: 1.0.3
Summary: Library Python untuk Instagram
Home-page: https://github.com/jepluk/instaspy
Author: Ivan Firmansyah
Keywords: instagram api library
Classifier: Programming Language :: Python :: 3
Classifier: License :: OSI Approved :: MIT License
Classifier: Operating System :: OS Independent
Requires-Python: >=3.6
Requires-Dist: requests
Dynamic: author
Dynamic: classifier
Dynamic: description
Dynamic: description-content-type
Dynamic: home-page
Dynamic: keywords
Dynamic: requires-dist
Dynamic: requires-python
Dynamic: summary
